skill_personal/LICENSE
skill_personal/LICENSE.md
skill_personal/README.md
skill_personal/__init__.py
skill_personal/skill.json
skill_personal/version.py
skill_personal/locale/ca-es/dialog/what_am_i.dialog
skill_personal/locale/ca-es/dialog/when_was_i_born.dialog
skill_personal/locale/ca-es/dialog/where_was_i_born.dialog
skill_personal/locale/ca-es/dialog/who_am_i.dialog
skill_personal/locale/ca-es/dialog/who_made_me.dialog
skill_personal/locale/ca-es/vocab/WhatAreYou.intent
skill_personal/locale/ca-es/vocab/WhenWereYouBorn.intent
skill_personal/locale/ca-es/vocab/WhereWereYouBorn.intent
skill_personal/locale/ca-es/vocab/WhoAreYou.intent
skill_personal/locale/ca-es/vocab/WhoMadeYou.intent
skill_personal/locale/cs-cz/dialog/what_am_i.dialog
skill_personal/locale/cs-cz/dialog/when_was_i_born.dialog
skill_personal/locale/cs-cz/dialog/where_was_i_born.dialog
skill_personal/locale/cs-cz/dialog/who_am_i.dialog
skill_personal/locale/cs-cz/dialog/who_made_me.dialog
skill_personal/locale/cs-cz/vocab/WhatAreYou.intent
skill_personal/locale/cs-cz/vocab/WhenWereYouBorn.intent
skill_personal/locale/cs-cz/vocab/WhereWereYouBorn.intent
skill_personal/locale/cs-cz/vocab/WhoAreYou.intent
skill_personal/locale/cs-cz/vocab/WhoMadeYou.intent
skill_personal/locale/da-dk/dialog/what_am_i.dialog
skill_personal/locale/da-dk/dialog/when_was_i_born.dialog
skill_personal/locale/da-dk/dialog/where_was_i_born.dialog
skill_personal/locale/da-dk/dialog/who_am_i.dialog
skill_personal/locale/da-dk/dialog/who_made_me.dialog
skill_personal/locale/da-dk/vocab/WhatAreYou.intent
skill_personal/locale/da-dk/vocab/WhenWereYouBorn.intent
skill_personal/locale/da-dk/vocab/WhereWereYouBorn.intent
skill_personal/locale/da-dk/vocab/WhoAreYou.intent
skill_personal/locale/da-dk/vocab/WhoMadeYou.intent
skill_personal/locale/de-de/dialog/what_am_i.dialog
skill_personal/locale/de-de/dialog/when_was_i_born.dialog
skill_personal/locale/de-de/dialog/where_was_i_born.dialog
skill_personal/neon_skill_personal.egg-info/PKG-INFO
skill_personal/neon_skill_personal.egg-info/SOURCES.txt
skill_personal/neon_skill_personal.egg-info/dependency_links.txt
skill_personal/neon_skill_personal.egg-info/entry_points.txt
skill_personal/neon_skill_personal.egg-info/requires.txt
skill_personal/neon_skill_personal.egg-info/top_level.txt
neon_skill_personal-1.0.3.dist-info/LICENSE
neon_skill_personal-1.0.3.dist-info/LICENSE.md
neon_skill_personal-1.0.3.dist-info/METADATA
neon_skill_personal-1.0.3.dist-info/WHEEL
neon_skill_personal-1.0.3.dist-info/entry_points.txt
neon_skill_personal-1.0.3.dist-info/top_level.txt
neon_skill_personal-1.0.3.dist-info/RECORD
